parsetta/__init__.py
parsetta/elements.py
parsetta/parsing.py
parsetta/utils.py
parsetta-0.0.6.dist-info/LICENSE
parsetta-0.0.6.dist-info/METADATA
parsetta-0.0.6.dist-info/WHEEL
parsetta-0.0.6.dist-info/top_level.txt
parsetta-0.0.6.dist-info/RECORD
